{
  "isin": "FR0050000829",
  "fund_name": "SG AMUNDI OBLIGATIONS VERTES",
  "lei": "969500TKG1TYT8BKXA62",
  "manager": "Soci\u00e9t\u00e9 G\u00e9n\u00e9rale Gestion",
  "sub_delegate": "Amundi",
  "domicile": "France",
  "currency": "EUR",
  "sfdr_article": "8",
  "fund_identifiers": {
    "pf_code": "PF85897",
    "cl_code": "CL85898",
    "um_code": "UM85896"
  },
  "language": "FRA",
  "document_count": 15,
  "documents": [
    {
      "original_filename": "PreContractualDocument_PF85897_FRA_FRA_20250526.pdf",
      "organized_filename": "PreContractualDocument_20250526.pdf",
      "document_type": "PreContractualDocument",
      "category": "sfdr",
      "priority": 3,
      "description": "SFDR Pre-contractual Annex",
      "date": "20250526",
      "checksum": "bbcb4764cd767d68c479577d704f02ad100e8655bb3cc5d2a75966d43510dbc0",
      "size_bytes": 348800,
      "source_zip": "documents_20260122204101.zip"
    },
    {
      "original_filename": "WebsiteSfdrDisclosure_PF85897_FRA_FRA_20250526.pdf",
      "organized_filename": "WebsiteSfdrDisclosure_20250526.pdf",
      "document_type": "WebsiteSfdrDisclosure",
      "category": "sfdr",
      "priority": 3,
      "description": "SFDR Website Disclosure (Art 10)",
      "date": "20250526",
      "checksum": "6e5d112dab0c4e203cd7d329ef11c8a4f6f0a87e52b60675031761b23fb8c164",
      "size_bytes": 136330,
      "source_zip": "documents_20260122204101.zip"
    },
    {
      "original_filename": "SfdrPeriodicAnnex_3712001_17842_FRA_FRA_20250531.pdf",
      "organized_filename": "SfdrPeriodicAnnex_20250531.pdf",
      "document_type": "SfdrPeriodicAnnex",
      "category": "sfdr",
      "priority": 3,
      "description": "SFDR Periodic Annex (Art 11)",
      "date": "20250531",
      "checksum": "18e01262b7c0ee33c8a043fdff8c3b1f2bf51599582c01444fbe283011c26fbf",
      "size_bytes": 636591,
      "source_zip": "documents_20260122204101.zip"
    },
    {
      "original_filename": "WebsiteSfdrDisclosureSummary_PF85897_FRA_FRA_20241220.pdf",
      "organized_filename": "WebsiteSfdrDisclosureSummary_20241220.pdf",
      "document_type": "WebsiteSfdrDisclosureSummary",
      "category": "sfdr",
      "priority": 2,
      "description": "SFDR Disclosure Summary",
      "date": "20241220",
      "checksum": "b1cbedaa05d27ec310afeb70d4038bb725228f1ebd9d8429189eb494bc5664ce",
      "size_bytes": 52885,
      "source_zip": "documents_20260122204101.zip"
    },
    {
      "original_filename": "PSC_1_UM85896_fra_FRA_20250526_20250525.pdf",
      "organized_filename": "PSC_20250525.pdf",
      "document_type": "PSC",
      "category": "prospectus",
      "priority": 3,
      "description": "Prospectus",
      "date": "20250525",
      "checksum": "68323a4ab887d3451af977550895d68c07a3ebb1ef836f01a9613861f0da7247",
      "size_bytes": 916795,
      "source_zip": "documents_20260122204056.zip"
    },
    {
      "original_filename": "PSC_1_UM85896_fra_FRA_20250526_20250526.pdf",
      "organized_filename": "PSC_20250526.pdf",
      "document_type": "PSC",
      "category": "prospectus",
      "priority": 3,
      "description": "Prospectus",
      "date": "20250526",
      "checksum": "337b97790cef4131930357c6f91c662c2c07d90793c22e3ebdc492f4f83399ba",
      "size_bytes": 1004633,
      "source_zip": "documents_20260122204056.zip"
    },
    {
      "original_filename": "MonthlyFactsheet_4142329_CL85898_FRA_FRA_AMUNDI_RETAIL_20251231.pdf",
      "organized_filename": "MonthlyFactsheet_20251231.pdf",
      "document_type": "MonthlyFactsheet",
      "category": "supplementary",
      "priority": 1,
      "description": "Monthly Factsheet",
      "date": "20251231",
      "checksum": "d1ebe3b254e51f84667e98c1a7de19e19c317922b64bf2437fc82453428b9313",
      "size_bytes": 557138,
      "source_zip": "documents_20260122204056.zip"
    },
    {
      "original_filename": "ClimateReport_4167820_PF85897_FRA_FRA_AMUNDI_20251231.pdf",
      "organized_filename": "ClimateReport_20251231.pdf",
      "document_type": "ClimateReport",
      "category": "supplementary",
      "priority": 1,
      "description": "Climate/TCFD Report",
      "date": "20251231",
      "checksum": "4be2001ca99c9e5e4095ce77ed81014a71cf48081f9ac6dd76afbd244945c33c",
      "size_bytes": 147272,
      "source_zip": "documents_20260122204056.zip"
    },
    {
      "original_filename": "KIDPRIIPs_803405_74269_FRA_FRA_20250526.pdf",
      "organized_filename": "KIDPRIIPs_20250526.pdf",
      "document_type": "KIDPRIIPs",
      "category": "supplementary",
      "priority": 1,
      "description": "KIID/PRIIPs KID",
      "date": "20250526",
      "checksum": "8accad0f2c31461fabf61ac3a6aa1b13c0bad31176ea3b6e24b95e85da3fb96c",
      "size_bytes": 163445,
      "source_zip": "documents_20260122204056.zip"
    },
    {
      "original_filename": "PreContractualDocument_PF85897_FRA_FRA_20250526.pdf",
      "organized_filename": "PreContractualDocument_20250526.pdf",
      "document_type": "PreContractualDocument",
      "category": "sfdr",
      "priority": 3,
      "description": "SFDR Pre-contractual Annex",
      "date": "20250526",
      "checksum": "bbcb4764cd767d68c479577d704f02ad100e8655bb3cc5d2a75966d43510dbc0",
      "size_bytes": 348800,
      "source_zip": "documents_20260122204056.zip"
    },
    {
      "original_filename": "SRITransparencyCode_CL85898_FRA_FRA_20250515.pdf",
      "organized_filename": "SRITransparencyCode_20250515.pdf",
      "document_type": "SRITransparencyCode",
      "category": "supplementary",
      "priority": 1,
      "description": "SRI Transparency Code",
      "date": "20250515",
      "checksum": "209e394daa1ff3e57355349b635b9cc221d1f92071bcb7da1d3a644af2ac58e4",
      "size_bytes": 7804691,
      "source_zip": "documents_20260122204056.zip"
    },
    {
      "original_filename": "WebsiteSfdrDisclosure_PF85897_FRA_FRA_20250526.pdf",
      "organized_filename": "WebsiteSfdrDisclosure_20250526.pdf",
      "document_type": "WebsiteSfdrDisclosure",
      "category": "sfdr",
      "priority": 3,
      "description": "SFDR Website Disclosure (Art 10)",
      "date": "20250526",
      "checksum": "6e5d112dab0c4e203cd7d329ef11c8a4f6f0a87e52b60675031761b23fb8c164",
      "size_bytes": 136330,
      "source_zip": "documents_20260122204056.zip"
    },
    {
      "original_filename": "SfdrPeriodicAnnex_3712001_17842_FRA_FRA_20250531.pdf",
      "organized_filename": "SfdrPeriodicAnnex_20250531.pdf",
      "document_type": "SfdrPeriodicAnnex",
      "category": "sfdr",
      "priority": 3,
      "description": "SFDR Periodic Annex (Art 11)",
      "date": "20250531",
      "checksum": "18e01262b7c0ee33c8a043fdff8c3b1f2bf51599582c01444fbe283011c26fbf",
      "size_bytes": 636591,
      "source_zip": "documents_20260122204056.zip"
    },
    {
      "original_filename": "RA_SG-AMUNDI-OBLIGATIONS-VERTES_202505_FRANCAIS_EUR_7705_xxx_1_xxx_117481.pdf",
      "organized_filename": "RA_unknown.pdf",
      "document_type": "RA",
      "category": "annual_report",
      "priority": 3,
      "description": "Rapport Annuel",
      "date": "unknown",
      "checksum": "5cc51b1860c3de01f3155e6c5fedb7ac2808530a16c082b81a14b25a04553011",
      "size_bytes": 4082674,
      "source_zip": "documents_20260122204056.zip"
    },
    {
      "original_filename": "WebsiteSfdrDisclosureSummary_PF85897_FRA_FRA_20241220.pdf",
      "organized_filename": "WebsiteSfdrDisclosureSummary_20241220.pdf",
      "document_type": "WebsiteSfdrDisclosureSummary",
      "category": "sfdr",
      "priority": 2,
      "description": "SFDR Disclosure Summary",
      "date": "20241220",
      "checksum": "b1cbedaa05d27ec310afeb70d4038bb725228f1ebd9d8429189eb494bc5664ce",
      "size_bytes": 52885,
      "source_zip": "documents_20260122204056.zip"
    }
  ],
  "organized_at": "2026-01-22T19:47:54.384492Z",
  "source_url": "https://www.societegeneralegestion.fr/fra/fr/particuliers/products/FR0050000829"
}